protego_cli-1.2.24.data/scripts/protegocli
protegocli/__init__.py
protegocli/arn.py
protegocli/aws_helper.py
protegocli/cli_logger.py
protegocli/config_generator.py
protegocli/fsp_downloader.py
protegocli/manifest_reader.py
protegocli/protego_config.py
protegocli/protego_fsp_layer.py
protego_cli-1.2.24.dist-info/LICENSE
protego_cli-1.2.24.dist-info/METADATA
protego_cli-1.2.24.dist-info/WHEEL
protego_cli-1.2.24.dist-info/top_level.txt
protego_cli-1.2.24.dist-info/RECORD
