Metadata-Version: 2.1
Name: protego-cli
Version: 1.2.24
Summary: Protego CLI wrapper
Home-page: https://www.protego.io
Author: Protego Labs
Author-email: support@protego.io
License: UNKNOWN
Platform: UNKNOWN
Classifier: Programming Language :: Python :: 2
Classifier: Programming Language :: Python :: 2.7
Classifier: License :: OSI Approved :: MIT License
Classifier: Operating System :: OS Independent
Requires-Dist: boto3 (>=1.9.60)
Requires-Dist: requests (>=2.21.0)
Requires-Dist: pyaml (>=18.11.0)
